stone_linux/__init__.py
stone_linux/cli.py
stone_linux/config.py
stone_linux/installer.py
stone_linux/py.typed
stone_linux/verify.py
stone_linux/examples/__init__.py
stone_linux/examples/benchmark.py
stone_linux/examples/langchain_example.py
stone_linux/examples/vllm_example.py
stone_linux-2.10.0a0.dist-info/licenses/LICENSE
stone_linux-2.10.0a0.dist-info/METADATA
stone_linux-2.10.0a0.dist-info/WHEEL
stone_linux-2.10.0a0.dist-info/entry_points.txt
stone_linux-2.10.0a0.dist-info/top_level.txt
stone_linux-2.10.0a0.dist-info/RECORD
