Metadata-Version: 2.4
Name: stone-linux
Version: 2.10.0a0
Summary: PyTorch 2.10 with native SM 12.0 (Blackwell) support for NVIDIA RTX 50-series GPUs
Home-page: https://github.com/kentstone84/PyTorch-2.10.0a0-for-Linux-
Author: PyTorch RTX Community
Author-email: PyTorch RTX Community <kentstone84@users.noreply.github.com>
Maintainer-email: PyTorch RTX Community <kentstone84@users.noreply.github.com>
License: BSD-3-Clause
Project-URL: Homepage, https://github.com/kentstone84/PyTorch-2.10.0a0-for-Linux-
Project-URL: Documentation, https://github.com/kentstone84/PyTorch-2.10.0a0-for-Linux-/blob/main/README.md
Project-URL: Repository, https://github.com/kentstone84/PyTorch-2.10.0a0-for-Linux-
Project-URL: Issues, https://github.com/kentstone84/PyTorch-2.10.0a0-for-Linux-/issues
Project-URL: Changelog, https://github.com/kentstone84/PyTorch-2.10.0a0-for-Linux-/releases
Keywords: pytorch,machine-learning,deep-learning,gpu,cuda,rtx-5090,rtx-5080,rtx-5070,blackwell,sm120,nvidia
Classifier: Development Status :: 4 - Beta
Classifier: Intended Audience :: Developers
Classifier: Intended Audience :: Science/Research
Classifier: License :: OSI Approved :: BSD License
Classifier: Operating System :: POSIX :: Linux
Classifier: Programming Language :: Python :: 3
Classifier: Programming Language :: Python :: 3.10
Classifier: Programming Language :: Python :: 3.11
Classifier: Programming Language :: Python :: 3.12
Classifier: Programming Language :: Python :: 3.13
Classifier: Programming Language :: Python :: 3.14
Classifier: Topic :: Scientific/Engineering :: Artificial Intelligence
Classifier: Topic :: Software Development :: Libraries :: Python Modules
Requires-Python: >=3.10
License-File: LICENSE
Requires-Dist: numpy>=2.0.0
Requires-Dist: packaging>=24.0
Requires-Dist: PyYAML>=6.0
Requires-Dist: typing-extensions>=4.8.0
Requires-Dist: requests>=2.31.0
Requires-Dist: tqdm>=4.66.0
Provides-Extra: dev
Requires-Dist: pytest>=7.4.0; extra == "dev"
Requires-Dist: black>=23.0.0; extra == "dev"
Requires-Dist: ruff>=0.1.0; extra == "dev"
Requires-Dist: mypy>=1.7.0; extra == "dev"
Provides-Extra: examples
Requires-Dist: jupyter>=1.0.0; extra == "examples"
Requires-Dist: notebook>=7.0.0; extra == "examples"
Requires-Dist: matplotlib>=3.8.0; extra == "examples"
Requires-Dist: pandas>=2.1.0; extra == "examples"
Provides-Extra: vllm
Requires-Dist: vllm>=0.6.0; extra == "vllm"
Provides-Extra: langchain
Requires-Dist: langchain>=0.1.0; extra == "langchain"
Requires-Dist: langchain-community>=0.0.1; extra == "langchain"
Dynamic: author
Dynamic: home-page
Dynamic: license-file
Dynamic: requires-python
